score.session-0.5.3-py3.7-nspkg.pth
score/session/__init__.py
score/session/_init.py
score/session/_kvcache.py
score/session/orm.py
score.session-0.5.3.dist-info/COPYING.LESSER.txt
score.session-0.5.3.dist-info/METADATA
score.session-0.5.3.dist-info/WHEEL
score.session-0.5.3.dist-info/namespace_packages.txt
score.session-0.5.3.dist-info/top_level.txt
score.session-0.5.3.dist-info/RECORD
